deepbase/__init__.py
deepbase/main.py
deepbase/parsers.py
deepbase/toon.py
deepbase-1.4.0.dist-info/licenses/LICENSE
deepbase-1.4.0.dist-info/METADATA
deepbase-1.4.0.dist-info/WHEEL
deepbase-1.4.0.dist-info/entry_points.txt
deepbase-1.4.0.dist-info/top_level.txt
deepbase-1.4.0.dist-info/RECORD
