Metadata-Version: 2.4
Name: deepbase
Version: 1.4.0
Summary: A CLI utility to consolidate project context for LLMs.
Author-email: Your Name <your@email.com>
License:                     GNU GENERAL PUBLIC LICENSE
Project-URL: Homepage, https://github.com/follen99/deepbase
Project-URL: Bug Tracker, https://github.com/follen99/deepbase/issues
Keywords: llm,context,developer-tool,ai,code-analysis,deepbase
Classifier: Programming Language :: Python :: 3
Classifier: License :: OSI Approved :: GNU General Public License v3 (GPLv3)
Classifier: Operating System :: OS Independent
Classifier: Topic :: Software Development
Classifier: Topic :: Utilities
Requires-Python: >=3.8
License-File: LICENSE
Requires-Dist: typer[all]
Requires-Dist: rich
Requires-Dist: tomli
Requires-Dist: chardet
Provides-Extra: dev
Requires-Dist: pytest; extra == "dev"
Provides-Extra: docs
Requires-Dist: mkdocs>=1.5.0; extra == "docs"
Requires-Dist: mkdocs-material>=9.5.0; extra == "docs"
Requires-Dist: mkdocstrings[python]>=0.24.0; extra == "docs"
Dynamic: license-file
